NaviNIBS/__init__.py
NaviNIBS/Devices/__init__.py
NaviNIBS/Devices/IGTLinkToolPositionsServer.py
NaviNIBS/Devices/PlusDeviceSet_Server_NDIPolarisVega_Network_Basic.xml
NaviNIBS/Devices/PlusDeviceSet_Server_NDIPolarisVega_Serial_Basic.xml
NaviNIBS/Devices/PlusDeviceSet_Server_NDIPolarisVega_Serial_Cobot.xml
NaviNIBS/Devices/ToolPositionsClient.py
NaviNIBS/Devices/ToolPositionsServer.py
NaviNIBS/Navigator/__init__.py
NaviNIBS/Navigator/GUI/__init__.py
NaviNIBS/Navigator/GUI/CollectionModels/__init__.py
NaviNIBS/Navigator/GUI/CollectionModels/DigitizedLocationsTableModel.py
NaviNIBS/Navigator/GUI/CollectionModels/FiducialsTableModels.py
NaviNIBS/Navigator/GUI/CollectionModels/HeadPointsTableModel.py
NaviNIBS/Navigator/GUI/CollectionModels/HotkeysTableModel.py
NaviNIBS/Navigator/GUI/CollectionModels/SamplesTableModel.py
NaviNIBS/Navigator/GUI/CollectionModels/TargetsTableModel.py
NaviNIBS/Navigator/GUI/CollectionModels/ToolsTableModel.py
NaviNIBS/Navigator/GUI/EditWindows/__init__.py
NaviNIBS/Navigator/GUI/EditWindows/CoilCalibrationWindow.py
NaviNIBS/Navigator/GUI/EditWindows/ImportSessionWindow.py
NaviNIBS/Navigator/GUI/EditWindows/PointerCalibrationWindow.py
NaviNIBS/Navigator/GUI/EditWindows/ToolCalibrationWindow.py
NaviNIBS/Navigator/GUI/NavigatorGUI.py
NaviNIBS/Navigator/GUI/resources/NaviNIBSIcon.ico
NaviNIBS/Navigator/GUI/resources/NaviNIBSIcon.svg
NaviNIBS/Navigator/GUI/ViewPanels/__init__.py
NaviNIBS/Navigator/GUI/ViewPanels/CameraPanel.py
NaviNIBS/Navigator/GUI/ViewPanels/CoordinateSystemsPanel.py
NaviNIBS/Navigator/GUI/ViewPanels/DigitizeLocationsPanel.py
NaviNIBS/Navigator/GUI/ViewPanels/FiducialsPanel.py
NaviNIBS/Navigator/GUI/ViewPanels/HeadModelPanel.py
NaviNIBS/Navigator/GUI/ViewPanels/MainViewPanelWithDockWidgets.py
NaviNIBS/Navigator/GUI/ViewPanels/ManageSessionPanel.py
NaviNIBS/Navigator/GUI/ViewPanels/MRIPanel.py
NaviNIBS/Navigator/GUI/ViewPanels/NavigatePanel/__init__.py
NaviNIBS/Navigator/GUI/ViewPanels/NavigatePanel/NavigatePanel.py
navinibs-0.2.4.dist-info/COPYING
navinibs-0.2.4.dist-info/COPYING.LESSER
navinibs-0.2.4.dist-info/entry_points.txt
navinibs-0.2.4.dist-info/METADATA
navinibs-0.2.4.dist-info/WHEEL
navinibs-0.2.4.dist-info/RECORD
