Metadata-Version: 2.3
Name: NaviNIBS
Version: 0.2.4
Summary: Software for neuronavigated non-invasive brain stimulation
License: LGPL-3.0-only
Author: Christopher C. Cline
Author-email: chriscline@users.noreply.github.com
Requires-Python: >=3.12,<3.14
Classifier: License :: OSI Approved :: GNU Lesser General Public License v3 or later (LGPLv3+)
Requires-Dist: PySide6 (>=6.9.1,<7.0.0)
Requires-Dist: QtAwesome (>=1.4.0,<2.0.0)
Requires-Dist: QtPy (>=2.4.3,<3.0.0)
Requires-Dist: attrs (>=25.1.0,<26.0.0)
Requires-Dist: concurrent-log-handler (>=0.9.28,<0.10.0)
Requires-Dist: darkdetect (>=0.8.0,<0.9.0)
Requires-Dist: jsbeautifier (>=1.14.6,<2.0.0)
Requires-Dist: keyboard (>=0.13.5,<0.14.0)
Requires-Dist: matplotlib (>=3.10.5,<4.0.0)
Requires-Dist: nibabel (>=5.3.2,<6.0.0)
Requires-Dist: nitransforms (>=25.0.0,<26.0.0)
Requires-Dist: numpy (>=2.3.2,<3.0.0)
Requires-Dist: pandas (>=2.3.1,<3.0.0)
Requires-Dist: platformdirs (>=4.2.2,<5.0.0)
Requires-Dist: pyigtl (>=0.3.1,<0.4.0)
Requires-Dist: pylsl (>=1.16.2,<2.0.0)
Requires-Dist: pyqtgraph (==0.13.3)
Requires-Dist: pyshortcuts (>=1.9.5,<2.0.0)
Requires-Dist: pytransform3d (>=3.14.2,<4.0.0)
Requires-Dist: pyvista (>=0.46.1,<0.47.0)
Requires-Dist: pyvistaqt (>=0.11.3,<0.12.0)
Requires-Dist: pyzmq (>=27.0.1,<28.0.0)
Requires-Dist: rmsd (>=1.5.1,<2.0.0)
Requires-Dist: scikit-spatial (>=9.0.1,<10.0.0)
Requires-Dist: simpleicp (>=2.0.14,<3.0.0)
Requires-Dist: vtk (>=9.5.0,<10.0.0)
Requires-Dist: xmltodict (>=0.14.2,<0.15.0)
Project-URL: Documentation, https://precisionneurolab.github.io/navinibs-docs
Project-URL: Repository, https://github.com/PrecisionNeuroLab/NaviNIBS
